cutci/__init__.py
cutci/cli.py
cutci/cos_sza.py
cutci/cutci.py
cutci_fuse/__init__.py
cutci_fuse/cutci_fuse.py
cutci-1.0.1.dist-info/AUTHORS.rst
cutci-1.0.1.dist-info/LICENSE
cutci-1.0.1.dist-info/METADATA
cutci-1.0.1.dist-info/WHEEL
cutci-1.0.1.dist-info/entry_points.txt
cutci-1.0.1.dist-info/top_level.txt
cutci-1.0.1.dist-info/RECORD
