Metadata-Version: 2.1
Name: cutci
Version: 1.0.1
Summary: Cutci is a library to calculate Human Thermal Comfort Index (UTCI) by GPU-accelerated computing with CuPy.
Home-page: https://github.com/jianhongdeng/cutci
Author: Hongdeng Jian
Author-email: jianhd@radi.ac.cn
License: Apache Software License 2.0
Keywords: cutci
Classifier: Development Status :: 2 - Pre-Alpha
Classifier: Intended Audience :: Developers
Classifier: License :: OSI Approved :: Apache Software License
Classifier: Natural Language :: English
Classifier: Programming Language :: Python :: 3
Classifier: Programming Language :: Python :: 3.6
Classifier: Programming Language :: Python :: 3.7
Classifier: Programming Language :: Python :: 3.8
Requires-Python: >=3.6
License-File: LICENSE
License-File: AUTHORS.rst
Requires-Dist: click (==8.1.3)
Requires-Dist: cupy (==13.0.0)
Requires-Dist: numpy (==1.24.3)
Requires-Dist: setuptools (==67.7.2)
